scubas/__init__.py
scubas/cables.py
scubas/conductivity.py
scubas/currents.py
scubas/datasets.py
scubas/models.py
scubas/plotlib.py
scubas/utils.py
scubas/sources/__init__.py
scubas/sources/current_sources.py
scubas-0.1.6.dist-info/LICENSE
scubas-0.1.6.dist-info/METADATA
scubas-0.1.6.dist-info/WHEEL
scubas-0.1.6.dist-info/top_level.txt
scubas-0.1.6.dist-info/RECORD
