Metadata-Version: 2.1
Name: scubas
Version: 0.1.6
Summary: SCUBAS: Submarine Cables Upset by Auroral Streams.
Home-page: https://github.com/shibaji7/SCUBAS
Author: Shibaji Chakraborty
Author-email: shibaji7@vt.edu
Maintainer: Shibaji Chakraborty
Maintainer-email: shibaji7@vt.edu
License: MIT License
Project-URL: Documentations, https://scubas.readthedocs.io/en/latest/
Keywords: Python>=3.6,submarine cable,electrical surge,geomagnetic induction,geomagnetic disturbance
Classifier: Development Status :: 3 - Alpha
Classifier: Intended Audience :: Education
Classifier: Programming Language :: Python :: 3
Classifier: Programming Language :: Python :: 3.6
Classifier: Programming Language :: Python :: 3.7
Classifier: Programming Language :: Python :: 3.8
Classifier: Programming Language :: Python :: 3.9
Classifier: Programming Language :: Python :: 3.10
Classifier: Operating System :: OS Independent
License-File: LICENSE
Requires-Dist: pandas
Requires-Dist: matplotlib (>=3.3.4)
Requires-Dist: pyproj
Requires-Dist: loguru
Requires-Dist: scipy
Requires-Dist: SciencePlots
